LICENSE
MANIFEST.in
README.md
README_cn.md
requirements.txt
setup.py
DWords/__init__.py
DWords/__main__.py
DWords/app.py
DWords/async_thread.py
DWords/danmaku.py
DWords/db.py
DWords/home.py
DWords/launcher.py
DWords/mail.py
DWords/migrate.py
DWords/setting.py
DWords/synchronizer.py
DWords/utils.py
DWords/version.py
DWords.egg-info/PKG-INFO
DWords.egg-info/SOURCES.txt
DWords.egg-info/dependency_links.txt
DWords.egg-info/entry_points.txt
DWords.egg-info/requires.txt
DWords.egg-info/top_level.txt
DWords/data/dictionary.db
DWords/img/logo.svg
tests/__init__.py
tests/test_danmaku.py
tests/test_home.py
tests/test_other.py
tests/test_setting.py
tests/test_sync.py