Metadata-Version: 2.1
Name: DWords
Version: 0.2.0
Summary: Show words as Danmaku in the screen to helps you remember them.
Home-page: https://github.com/luyuhuang/DWords
Author: Luyu Huang
Author-email: luyu_huang@foxmail.com
License: GPLv3
Keywords: danmaku words english-learning vocabulary pyqt5
Platform: UNKNOWN
Classifier: Intended Audience :: Education
Classifier: License :: OSI Approved :: GNU General Public License v3 (GPLv3)
Classifier: Natural Language :: English
Classifier: Operating System :: Microsoft :: Windows
Classifier: Operating System :: MacOS
Classifier: Operating System :: POSIX :: Linux
Classifier: Programming Language :: Python :: 3.6
Classifier: Programming Language :: Python :: 3.7
Classifier: Programming Language :: Python :: 3.8
Classifier: Programming Language :: Python :: 3 :: Only
